Simulations/ProgramCounter/ProgramCounter.sv
module ProgramCounter (
    input wire clk,
    input logic [31:0] pc_input,
    output logic [31:0] pc_out
);

    logic first_time = 1'b1; // Variable para controlar la primera vez

    always_ff @(posedge clk) begin
        if (first_time) begin
            pc_out <= 32'h00000000; // Si es la primera vez, establece pc_out en 0
            first_time <= 1'b0; // Desactiva la señal de primera vez
        end else begin
            pc_out <= pc_input; // De lo contrario, sigue pc_input
        end
    end

endmodule

Simulations/ProgramCounter/ProgramCounterTest.sv
`timescale 1ns/1ns

module ProgramCounter_tb;

    // Parámetros del módulo
    localparam CLK_PERIOD = 10;  // Período del reloj en unidades de tiempo (en este caso, 10ns)
    localparam SIM_TIME = 200;   // Tiempo total de simulación en unidades de tiempo

    // Señales del test bench
    reg clk = 0;                // Señal de reloj
    reg [31:0] pc_input = 0;    // Señal de entrada pc_input
    wire [31:0] pc_out;         // Señal de salida pc_out

    // Instanciación del módulo bajo prueba
    ProgramCounter dut (
        .clk(clk),
        .pc_input(pc_input),
        .pc_out(pc_out)
    );

    // Generación del reloj
    always #((CLK_PERIOD)/2) clk = ~clk;

    // Generación del archivo VCD
    initial begin
        $dumpfile("ProgramCounter_tb.vcd");
        $dumpvars(0, ProgramCounter_tb);
    end

    // Cambio de pc_input para observar el cambio en pc_out
    initial begin
        // Inicialización
        // Cambios en pc_input
        #0   pc_input = 32'h00000000;
        #10  pc_input = 32'h00000001;
        #10  pc_input = 32'h00000002;
        #10  pc_input = 32'h00000003;
        #10  pc_input = 32'h00000004;
        #10  pc_input = 32'h00000005;
        #10  pc_input = 32'h00000006;
        #10  pc_input = 32'h00000007;
        #10  pc_input = 32'h00000008;
        #10  pc_input = 32'h00000009;
        #10  pc_input = 32'h0000000A;
        #10  pc_input = 32'h0000000B;
        #10  pc_input = 32'h0000000C;
        #10  pc_input = 32'h0000000D;
        #10  pc_input = 32'h0000000E;
        #10  pc_input = 32'h0000000F;
        $finish;
    end

    // Finalización de la simulación
    always @(posedge clk) begin
        if ($time == SIM_TIME) begin
            $display("Fin de la simulación.");
            $finish;
        end
    end

endmodule

Simulations/ProgramCounter/ProgramCounter_tb.vcd
$date
	Mon Apr 29 13:40:07 2024
$end
$version
	Icarus Verilog
$end
$timescale
	1ns
$end
$scope module ProgramCounter_tb $end
$var wire 32 ! pc_out [31:0] $end
$var reg 1 " clk $end
$var reg 32 # pc_input [31:0] $end
$scope module dut $end
$var wire 1 " clk $end
$var wire 32 $ pc_input [31:0] $end
$var reg 1 % first_time $end
$var reg 32 & pc_out [31:0] $end
$upscope $end
$upscope $end
$enddefinitions $end
#0
$dumpvars
bx &
1%
b0 $
b0 #
0"
bx !
$end
#5
0%
b0 !
b0 &
1"
#10
0"
b1 #
b1 $
#15
b1 !
b1 &
1"
#20
0"
b10 #
b10 $
#25
b10 !
b10 &
1"
#30
0"
b11 #
b11 $
#35
b11 !
b11 &
1"
#40
0"
b100 #
b100 $
#45
b100 !
b100 &
1"
#50
0"
b101 #
b101 $
#55
b101 !
b101 &
1"
#60
0"
b110 #
b110 $
#65
b110 !
b110 &
1"
#70
0"
b111 #
b111 $
#75
b111 !
b111 &
1"
#80
0"
b1000 #
b1000 $
#85
b1000 !
b1000 &
1"
#90
0"
b1001 #
b1001 $
#95
b1001 !
b1001 &
1"
#100
0"
b1010 #
b1010 $
#105
b1010 !
b1010 &
1"
#110
0"
b1011 #
b1011 $
#115
b1011 !
b1011 &
1"
#120
0"
b1100 #
b1100 $
#125
b1100 !
b1100 &
1"
#130
0"
b1101 #
b1101 $
#135
b1101 !
b1101 &
1"
#140
0"
b1110 #
b1110 $
#145
b1110 !
b1110 &
1"
#150
0"
b1111 #
b1111 $
